ab_client/token_store/__init__.py
ab_client/token_store/clients/__init__.py
ab_client/token_store/clients/async_client.py
ab_client/token_store/clients/sync_client.py
ab_client/token_store/exceptions/__init__.py
ab_client/token_store/exceptions/http_exception.py
ab_client/token_store/models/CreateOAuth2TokenRequest.py
ab_client/token_store/models/HTTPValidationError.py
ab_client/token_store/models/ManagedOAuth2Token.py
ab_client/token_store/models/OAuth2Token.py
ab_client/token_store/models/ValidationError.py
ab_client/token_store/models/__init__.py
ab_client_token_store-1.1.0.dist-info/METADATA
ab_client_token_store-1.1.0.dist-info/WHEEL
ab_client_token_store-1.1.0.dist-info/licenses/LICENSE
ab_client_token_store-1.1.0.dist-info/RECORD
